MediaInfo.py
README.rst
setup.py
MediaInfo.egg-info/PKG-INFO
MediaInfo.egg-info/SOURCES.txt
MediaInfo.egg-info/dependency_links.txt
MediaInfo.egg-info/top_level.txt
tests/__init__.py
tests/tests.py