Metadata-Version: 1.1
Name: MediaInfo
Version: 0.0.1
Summary: A Python wrapper around the ffprobe or mediainfo command line utility
Home-page: https://github.com/laodifang/MediaInfo
Author: Ren Peng
Author-email: ithink.ren@gmail.com
License: MIT
Keywords: Python ffmpeg ffprobe mediainfo
Platform: UNKNOWN
Classifier: Development Status :: 5 - Production/Stable
Classifier: Intended Audience :: Developers
Classifier: License :: OSI Approved :: MIT License
Classifier: Programming Language :: Python :: 3.4
Classifier: Programming Language :: Python :: 3 :: Only
